spider_toolbox/decrypt_tools.py
spider_toolbox/file_tools.py
spider_toolbox/requests_tools.py
spider_toolbox/anime_api/cycdm.py
spider_toolbox-0.0.32.dist-info/LICENSE
spider_toolbox-0.0.32.dist-info/METADATA
spider_toolbox-0.0.32.dist-info/WHEEL
spider_toolbox-0.0.32.dist-info/top_level.txt
spider_toolbox-0.0.32.dist-info/RECORD
