Metadata-Version: 2.1
Name: spider-toolbox
Version: 0.0.32
Summary: 爬虫工具库
Home-page: https://github.com/sweetnotice/spider_toolbox
Author: neco_arc
Author-email: 3306601284@qq.com
Classifier: Programming Language :: Python :: 3
Classifier: License :: OSI Approved :: MIT License
Classifier: Operating System :: OS Independent
Requires-Python: >=3.6
License-File: LICENSE
Requires-Dist: requests
Requires-Dist: PyExecJS
Requires-Dist: rich
Requires-Dist: pycryptodome
